odoo8_addon_asterisk_click2dial_crm-8.0.0.1.0-py2.7-nspkg.pth
odoo_addons/asterisk_click2dial_crm/__openerp__.py
odoo_addons/asterisk_click2dial_crm/__init__.py
odoo8_addon_asterisk_click2dial_crm-8.0.0.1.0.dist-info/top_level.txt
odoo8_addon_asterisk_click2dial_crm-8.0.0.1.0.dist-info/WHEEL
odoo8_addon_asterisk_click2dial_crm-8.0.0.1.0.dist-info/RECORD
odoo8_addon_asterisk_click2dial_crm-8.0.0.1.0.dist-info/metadata.json
odoo8_addon_asterisk_click2dial_crm-8.0.0.1.0.dist-info/DESCRIPTION.rst
odoo8_addon_asterisk_click2dial_crm-8.0.0.1.0.dist-info/METADATA
odoo8_addon_asterisk_click2dial_crm-8.0.0.1.0.dist-info/namespace_packages.txt
